cinrad/__init__.py
cinrad/_typing.py
cinrad/_utils.c
cinrad/_utils.cp310-win_amd64.pyd
cinrad/calc.py
cinrad/common.py
cinrad/deprecation.py
cinrad/error.py
cinrad/grid.py
cinrad/hca.py
cinrad/projection.py
cinrad/utils.py
cinrad/correct/__init__.py
cinrad/correct/_unwrap_2d.c
cinrad/correct/_unwrap_2d.cp310-win_amd64.pyd
cinrad/correct/dealias.py
cinrad/correct/unwrap_2d_ljmu.c
cinrad/data/chinaCity.json
cinrad/data/hca_params.npy
cinrad/data/radar_station.json
cinrad/data/colormap/CC.cmap
cinrad/data/colormap/CC2.cmap
cinrad/data/colormap/CC_s.cmap
cinrad/data/colormap/ET.cmap
cinrad/data/colormap/HCL.cmap
cinrad/data/colormap/KDP.cmap
cinrad/data/colormap/KDP_s.cmap
cinrad/data/colormap/OHP.cmap
cinrad/data/colormap/REF.cmap
cinrad/data/colormap/REF_s.cmap
cinrad/data/colormap/VEL.cmap
cinrad/data/colormap/VEL_reverse.cmap
cinrad/data/colormap/VEL_s.cmap
cinrad/data/colormap/VIL.cmap
cinrad/data/colormap/ZDR.cmap
cinrad/data/colormap/ZDR_s.cmap
cinrad/io/__init__.py
cinrad/io/_dtype.py
cinrad/io/base.py
cinrad/io/export.py
cinrad/io/level2.py
cinrad/io/level3.py
cinrad/io/_radar_struct/CC.py
cinrad/io/_radar_struct/CC2.py
cinrad/io/_radar_struct/CD.py
cinrad/io/_radar_struct/PA.py
cinrad/io/_radar_struct/__init__.py
cinrad/io/_radar_struct/parse_spec.py
cinrad/io/_radar_struct/standard_data.py
cinrad/visualize/__init__.py
cinrad/visualize/gpf.py
cinrad/visualize/layout.py
cinrad/visualize/ppi.py
cinrad/visualize/rhi.py
cinrad/visualize/utils.py
cinrad-1.9.2.dist-info/licenses/LICENSE
cinrad-1.9.2.dist-info/METADATA
cinrad-1.9.2.dist-info/WHEEL
cinrad-1.9.2.dist-info/top_level.txt
cinrad-1.9.2.dist-info/RECORD
