Metadata-Version: 2.1
Name: cinrad
Version: 1.9.2
Summary: Decode CINRAD radar data and visualize
Author: Puyuan Du
Author-email: dpy274555447@gmail.com
License: GPL Licence
Platform: Windows
Requires-Python: >=3.5
License-File: LICENSE
Requires-Dist: metpy >=0.8
Requires-Dist: cartopy >=0.15
Requires-Dist: pyshp !=2.0.0,!=2.0.1
Requires-Dist: matplotlib >=2.2
Requires-Dist: vanadis
Requires-Dist: cinrad-data >=0.1
